{
  "version": 3,
  "middleware": {
    "/": {
      "files": [
        "server/edge-instrumentation.js",
        "server/edge-runtime-webpack.js",
        "server/src/middleware.js"
      ],
      "name": "src/middleware",
      "page": "/",
      "matchers": [
        {
          "regexp": "^(?:\\/(_next\\/data\\/[^/]{1,}))?(?:\\/((?!_next|login|api\\/auth|skill|favicon\\.ico|.*\\.).*))(\\.json)?[\\/#\\?]?$",
          "originalSource": "/((?!_next|login|api/auth|skill|favicon\\.ico|.*\\.).*)"
        }
      ],
      "wasm": [],
      "assets": [],
      "env": {
        "__NEXT_BUILD_ID": "xQz2CBSl5Hka6UqCTu9zD",
        "NEXT_SERVER_ACTIONS_ENCRYPTION_KEY": "XBPiapWMZ2ZCy1z9lLKL/sor8eCy7C1XeeqK5Dtx+Ik=",
        "__NEXT_PREVIEW_MODE_ID": "422f735f5237e8342d5f01f8eddd6767",
        "__NEXT_PREVIEW_MODE_SIGNING_KEY": "84e209e84ee2e420a9e0f69192df1ca2f6a0075a005e96e086f45e5f6ed2736b",
        "__NEXT_PREVIEW_MODE_ENCRYPTION_KEY": "c53192b668842eb6f58a77dba203cdebac0bc19b791ec7d036f6d75b1ede697f"
      }
    }
  },
  "functions": {},
  "sortedMiddleware": [
    "/"
  ]
}